statest/__init__.py
statest/quantile/__init__.py
statest/quantile/estimate.py
statest/quantile/expon_based_estimators.py
statest/quantile/perf_measurer.py
statest/quantile/some_distributions.py
statest/quantile/exponential/__init__.py
statest/quantile/exponential/estimator_racetrack.py
statest/quantile/exponential/estimator_racetrack2.py
statest/quantile/simulator/__init__.py
statest/quantile/simulator/estimator_racetrack.py
statest/quantile/simulator/estimator_racetrack1.py
statest/quantile/simulator/plot_maker.py
statest/quantile/simulator/simulator.py
statest-0.0.1.dist-info/LICENSE
statest-0.0.1.dist-info/METADATA
statest-0.0.1.dist-info/WHEEL
statest-0.0.1.dist-info/top_level.txt
statest-0.0.1.dist-info/RECORD
