Metadata-Version: 2.1
Name: statest
Version: 0.0.1
Summary: Statistical estimation.
Home-page: https://github.com/ryu577/statest
Author: Rohit Pandey
Author-email: rohitpandey576@gmail.com
License: MIT
Platform: UNKNOWN
